trasa/__init__.py
trasa/chopper.py
trasa/error.py
trasa/identifier.py
trasa/ip.py
trasa/ldp.py
trasa/ldp_message.py
trasa/ldp_pdu.py
trasa/ldp_state_machine.py
trasa/packing_tools.py
trasa/stream_server.py
trasa/tlv.py
trasa-0.0.1.dist-info/LICENSE
trasa-0.0.1.dist-info/METADATA
trasa-0.0.1.dist-info/WHEEL
trasa-0.0.1.dist-info/top_level.txt
trasa-0.0.1.dist-info/RECORD
