Metadata-Version: 2.1
Name: trasa
Version: 0.0.1
Summary: A prototype Python router daemon
Home-page: https://github.com/samrussell/trasa
Author: Sam Russell
Author-email: sam.h.russell@gmail.com
License: Affero GPL v3
Keywords: ldp trasa mpls routing sdn networking
Platform: UNKNOWN
Classifier: Development Status :: 3 - Alpha
Classifier: Intended Audience :: System Administrators
Classifier: License :: OSI Approved :: GNU Affero General Public License v3
Classifier: Programming Language :: Python :: 3
Requires-Python: >=3
Requires-Dist: eventlet
Requires-Dist: pyyaml
